replay_memory-0.2.0.dist-info/METADATA
replay_memory-0.2.0.dist-info/WHEEL
replay_memory/__init__.py
replay_memory/__init__.pyi
replay_memory/py.typed
replay_memory/replay_memory.abi3.so
replay_memory-0.2.0.dist-info/RECORD
